omero/plugins/zarr.py
omero_cli_zarr-0.6.1.dist-info/licenses/LICENSE.txt
omero_zarr/__init__.py
omero_zarr/_version.py
omero_zarr/cli.py
omero_zarr/masks.py
omero_zarr/raw_pixels.py
omero_zarr/util.py
omero_cli_zarr-0.6.1.dist-info/METADATA
omero_cli_zarr-0.6.1.dist-info/WHEEL
omero_cli_zarr-0.6.1.dist-info/top_level.txt
omero_cli_zarr-0.6.1.dist-info/RECORD
