Metadata-Version: 2.4
Name: omero-cli-zarr
Version: 0.6.1
Summary: Plugin for exporting images in zarr format.
Home-page: https://github.com/ome/omero-cli-zarr/
Author: The Open Microscopy Team
Author-email: 
Keywords: OMERO.CLI,plugin
Classifier: Development Status :: 3 - Alpha
Classifier: Environment :: Plugins
Classifier: Intended Audience :: Developers
Classifier: Intended Audience :: End Users/Desktop
Classifier: Intended Audience :: Information Technology
Classifier: License :: OSI Approved :: GNU General Public License v2 or later (GPLv2+)
Classifier: Natural Language :: English
Classifier: Operating System :: OS Independent
Classifier: Programming Language :: Python :: 3
Classifier: Topic :: Software Development :: Libraries :: Python Modules
Requires-Python: >=3
License-File: LICENSE.txt
Requires-Dist: omero-py>=5.6.0
Requires-Dist: ome-zarr<0.12.0,>=0.5.0
Dynamic: author
Dynamic: classifier
Dynamic: description
Dynamic: home-page
Dynamic: keywords
Dynamic: license-file
Dynamic: requires-dist
Dynamic: requires-python
Dynamic: summary
